Metadata-Version: 2.0
Name: django-notify-x2
Version: 0.7.0
Summary: Notification sytem for Django
Home-page: https://github.com/audiolion/django-notify-x2
Author: Vikas Yadav, Ryan Castner
Author-email: castner.rr@gmail.com
License: The MIT License
Keywords: django notifications,notify,facebook like notifications,github like notifications
Platform: OS Independent
Classifier: Development Status :: 5 - Production/Stable
Classifier: Framework :: Django :: 1.8
Classifier: Framework :: Django :: 1.9
Classifier: Framework :: Django :: 1.10
Classifier: Environment :: Web Environment
Classifier: Operating System :: OS Independent
Classifier: Programming Language :: Python :: 2.7
Classifier: Programming Language :: Python :: 3.4
Classifier: Intended Audience :: Developers
Requires-Dist: django (>=1.8)
Requires-Dist: django-jsonfield
Requires-Dist: six
Requires-Dist: twine
